LICENSE.txt
MANIFEST.in
README.md
setup.cfg
setup.py
phi/VERSION
phi/__init__.py
phi/_troubleshoot.py
phi/flow.py
phi/field/__init__.py
phi/field/_angular_velocity.py
phi/field/_embed.py
phi/field/_field.py
phi/field/_field_io.py
phi/field/_field_math.py
phi/field/_grid.py
phi/field/_mask.py
phi/field/_noise.py
phi/field/_point_cloud.py
phi/field/_resample.py
phi/field/_scene.py
phi/geom/__init__.py
phi/geom/_box.py
phi/geom/_convert.py
phi/geom/_cylinder.py
phi/geom/_double_cover.py
phi/geom/_embed.py
phi/geom/_functions.py
phi/geom/_geom.py
phi/geom/_geom_functions.py
phi/geom/_geom_ops.py
phi/geom/_graph.py
phi/geom/_grid.py
phi/geom/_heightmap.py
phi/geom/_mesh.py
phi/geom/_mesh_builder.py
phi/geom/_sdf.py
phi/geom/_sdf_grid.py
phi/geom/_sphere.py
phi/geom/_spline.py
phi/geom/_spline_sheet.py
phi/geom/_spline_solid.py
phi/geom/_transform.py
phi/geom/_voxels.py
phi/jax/__init__.py
phi/jax/flow.py
phi/jax/stax/__init__.py
phi/jax/stax/flow.py
phi/jax/stax/nets.py
phi/math/__init__.py
phi/math/backend.py
phi/math/extrapolation.py
phi/math/magic.py
phi/physics/__init__.py
phi/physics/_boundaries.py
phi/physics/advect.py
phi/physics/diffuse.py
phi/physics/fluid.py
phi/physics/integrate.py
phi/physics/sph.py
phi/tf/__init__.py
phi/tf/flow.py
phi/tf/nets.py
phi/torch/__init__.py
phi/torch/flow.py
phi/torch/nets.py
phi/vis/__init__.py
phi/vis/_io.py
phi/vis/_log.py
phi/vis/_plot_util.py
phi/vis/_user_namespace.py
phi/vis/_viewer.py
phi/vis/_vis.py
phi/vis/_vis_base.py
phi/vis/_console/__init__.py
phi/vis/_console/_console_gui.py
phi/vis/_console/_console_plot.py
phi/vis/_console/_console_util.py
phi/vis/_dash/__init__.py
phi/vis/_dash/_plotly_plots.py
phi/vis/_dash/board.py
phi/vis/_dash/colormaps.py
phi/vis/_dash/dash_app.py
phi/vis/_dash/dash_gui.py
phi/vis/_dash/info.py
phi/vis/_dash/log.py
phi/vis/_dash/model_controls.py
phi/vis/_dash/player_controls.py
phi/vis/_dash/viewer.py
phi/vis/_dash/viewsettings.py
phi/vis/_matplotlib/__init__.py
phiflow.egg-info/PKG-INFO
phiflow.egg-info/SOURCES.txt
phiflow.egg-info/dependency_links.txt
phiflow.egg-info/requires.txt
phiflow.egg-info/top_level.txt