Metadata-Version: 2.1
Name: phiflow
Version: 3.4.0
Summary: Differentiable PDE solving framework for machine learning
Home-page: https://github.com/tum-pbs/PhiFlow
Download-URL: https://github.com/tum-pbs/PhiFlow/archive/3.4.0.tar.gz
Author: Philipp Holl
Author-email: philipp.holl@tum.de
License: MIT
Keywords: Differentiable,Simulation,Fluid,Machine Learning,Deep Learning
Classifier: Development Status :: 5 - Production/Stable
Classifier: Intended Audience :: Developers
Classifier: Topic :: Software Development :: Build Tools
Classifier: License :: OSI Approved :: MIT License
Classifier: Programming Language :: Python :: 3
Classifier: Programming Language :: Python :: 3.10
Classifier: Programming Language :: Python :: 3.11
Classifier: Programming Language :: Python :: 3.12
License-File: LICENSE.txt
Requires-Dist: phiml>=1.14.0
Requires-Dist: matplotlib>=3.5.0
Requires-Dist: packaging
